[
  {
    "codice": "CA-Z-BI-L3-NA",
    "variante": "200426",
    "descrizione": "SPECIALE 3 Carota biologica da porzionare in classe - Data distribuzione: 22/04/2026",
    "display_qty": "16 Colli"
  },
  {
    "codice": "FO-DI-AS-04-LV",
    "variante": "",
    "descrizione": "SPECIALE 2 Asiago DOP - Data distribuzione: 23/04/2026 - Scad. min. 22/06/2026",
    "display_qty": "94 Fette"
  },
  {
    "codice": "FO-DI-GP-01-NI",
    "variante": "",
    "descrizione": "Grana Padano DOP a cubetti - 9 mesi - Data distribuzione: 23/04/2026 - Scad. min. 22/06/2026",
    "display_qty": "14 Colli"
  },
  {
    "codice": "FO-DI-PV-04-LB",
    "variante": "",
    "descrizione": "SPECIALE 1 Piave mezzano DOP - Data distribuzione: 23/04/2026 - Scad. min. 22/06/2026",
    "display_qty": "1 Colli e 10 Fette"
  },
  {
    "codice": "LT-AQ-04-LB",
    "variante": "",
    "descrizione": "Latte Intero alta qualit\u00e0 - Data distribuzione: 22/04/2026 - Scad. min. 25/04/2026",
    "display_qty": "2 Fardelli e 9 Bottiglie"
  },
  {
    "codice": "LT-AQ-04-LS",
    "variante": "",
    "descrizione": "Latte Intero alta qualit\u00e0 - Data distribuzione: 22/04/2026 - Scad. min. 25/04/2026",
    "display_qty": "2 Fardelli e 7 Bottiglie"
  },
  {
    "codice": "LT-AQ-04-LV",
    "variante": "",
    "descrizione": "Latte Intero alta qualit\u00e0 - Data distribuzione: 22/04/2026 - Scad. min. 25/04/2026",
    "display_qty": "44 Fardelli e 5 Bottiglie"
  },
  {
    "codice": "LT-DL-02-LC",
    "variante": "",
    "descrizione": "Latte UHT senza lattosio - Data distribuzione: 22/04/2026 - Scad. min. 07/05/2026",
    "display_qty": "55 Brick"
  },
  {
    "codice": "LT-ES-04-LS",
    "variante": "",
    "descrizione": "Latte Intero esl - Data distribuzione: 22/04/2026 - Scad. min. 07/05/2026",
    "display_qty": "18 Fardelli e 2 Bottiglie"
  },
  {
    "codice": "LT-ESL-IN-LB",
    "variante": "",
    "descrizione": "Latte intero ESL - Data distribuzione: 22/04/2026 - Scad. min. 07/05/2026",
    "display_qty": "21 Fardelli e 1 Bottiglie"
  },
  {
    "codice": "ME-S-DI-L3-NA",
    "variante": "200426",
    "descrizione": "SPECIALE 3 Mela di Val di Non DOP per estratto - Data distribuzione: 22/04/2026",
    "display_qty": "12 Colli"
  },
  {
    "codice": "ME-T-DI-V0-NA",
    "variante": "200426",
    "descrizione": "Mela di Val di Non DOP - Data distribuzione: 23/04/2026",
    "display_qty": "617 Colli"
  },
  {
    "codice": "YO-BI-MN-04-LB",
    "variante": "",
    "descrizione": "SPECIALE 2 Yogurt naturale bianco bio intero - Data distribuzione: 23/04/2026 - Scad. min. 08/05/2026",
    "display_qty": "49 Cartoni e 2 Cluster"
  },
  {
    "codice": "YO-DL-02-LC",
    "variante": "",
    "descrizione": "SPECIALE 2 Yogurt delattosato bianco - Data distribuzione: 23/04/2026 - Scad. min. 08/05/2026",
    "display_qty": "8 Cartoni e 5 Porzioni"
  }
]