{
  "data_elab": "19-06-2026",
  "tipo": "GRAND_CHEF",
  "deliveries": [
    {
      "codice_consegna": "100355080",
      "data": "19-06-2026",
      "num_ddt": "GC_100355080",
      "pdf_name": "100355080_19-06-2026.pdf",
      "tipo": "GRAND_CHEF",
      "zona": "GC_uOHxJZtf11XNKRCRQbSs",
      "gc_colli": "",
      "gc_peso_kg": "24.86",
      "gc_num_cartone": "",
      "orario_min": "07:00",
      "orario_max": "11:00",
      "note": ""
    },
    {
      "codice_consegna": "100343039",
      "data": "19-06-2026",
      "num_ddt": "GC_100343039",
      "pdf_name": "100343039_19-06-2026.pdf",
      "tipo": "GRAND_CHEF",
      "zona": "GC_uOHxJZtf11XNKRCRQbSs",
      "gc_colli": "2",
      "gc_peso_kg": "34.632",
      "gc_num_cartone": "218",
      "orario_min": "09:00",
      "orario_max": "12:00",
      "note": ""
    },
    {
      "codice_consegna": "100343112",
      "data": "19-06-2026",
      "num_ddt": "GC_100343112",
      "pdf_name": "100343112_19-06-2026.pdf",
      "tipo": "GRAND_CHEF",
      "zona": "GC_uOHxJZtf11XNKRCRQbSs",
      "gc_colli": "1",
      "gc_peso_kg": "32.88",
      "gc_num_cartone": "86",
      "orario_min": "06:30",
      "orario_max": "10:30",
      "note": "ENTRO LE 10:30"
    },
    {
      "codice_consegna": "100349140",
      "data": "19-06-2026",
      "num_ddt": "GC_100349140",
      "pdf_name": "100349140_19-06-2026.pdf",
      "tipo": "GRAND_CHEF",
      "zona": "GC_uOHxJZtf11XNKRCRQbSs",
      "gc_colli": "",
      "gc_peso_kg": "36.241",
      "gc_num_cartone": "24",
      "orario_min": "09:00",
      "orario_max": "11:30",
      "note": "30min. prima chiama 3387353343"
    },
    {
      "codice_consegna": "100333479",
      "data": "19-06-2026",
      "num_ddt": "GC_100333479",
      "pdf_name": "100333479_19-06-2026.pdf",
      "tipo": "GRAND_CHEF",
      "zona": "GC_uOHxJZtf11XNKRCRQbSs",
      "gc_colli": "",
      "gc_peso_kg": "41.59",
      "gc_num_cartone": "136",
      "orario_min": "",
      "orario_max": "14:00",
      "note": ""
    },
    {
      "codice_consegna": "100347819",
      "data": "19-06-2026",
      "num_ddt": "GC_100347819",
      "pdf_name": "100347819_19-06-2026.pdf",
      "tipo": "GRAND_CHEF",
      "zona": "GC_uOHxJZtf11XNKRCRQbSs",
      "gc_colli": "1",
      "gc_peso_kg": "43.346",
      "gc_num_cartone": "140",
      "orario_min": "08:00",
      "orario_max": "13:00",
      "note": "fino ore 17:00"
    },
    {
      "codice_consegna": "100325476",
      "data": "19-06-2026",
      "num_ddt": "GC_100325476",
      "pdf_name": "100325476_19-06-2026.pdf",
      "tipo": "GRAND_CHEF",
      "zona": "GC_uOHxJZtf11XNKRCRQbSs",
      "gc_colli": "",
      "gc_peso_kg": "126.794",
      "gc_num_cartone": "144",
      "orario_min": "06:30",
      "orario_max": "09:30",
      "note": ""
    },
    {
      "codice_consegna": "100340952",
      "data": "19-06-2026",
      "num_ddt": "GC_100340952",
      "pdf_name": "100340952_19-06-2026.pdf",
      "tipo": "GRAND_CHEF",
      "zona": "GC_uOHxJZtf11XNKRCRQbSs",
      "gc_colli": "",
      "gc_peso_kg": "72.592",
      "gc_num_cartone": "192",
      "orario_min": "09:00",
      "orario_max": "11:00",
      "note": "TASSATIVO NON PRIMA DELLE 09"
    },
    {
      "codice_consegna": "100342652",
      "data": "19-06-2026",
      "num_ddt": "GC_100342652",
      "pdf_name": "100342652_19-06-2026.pdf",
      "tipo": "GRAND_CHEF",
      "zona": "GC_uOHxJZtf11XNKRCRQbSs",
      "gc_colli": "",
      "gc_peso_kg": "20.89",
      "gc_num_cartone": "127",
      "orario_min": "08:00",
      "orario_max": "11:00",
      "note": ""
    },
    {
      "codice_consegna": "100352531",
      "data": "19-06-2026",
      "num_ddt": "GC_100352531",
      "pdf_name": "100352531_19-06-2026.pdf",
      "tipo": "GRAND_CHEF",
      "zona": "GC_uOHxJZtf11XNKRCRQbSs",
      "gc_colli": "",
      "gc_peso_kg": "15.996",
      "gc_num_cartone": "",
      "orario_min": "07:00",
      "orario_max": "10:00",
      "note": "consegnare entro le 10:00"
    },
    {
      "codice_consegna": "100354449",
      "data": "19-06-2026",
      "num_ddt": "GC_100354449",
      "pdf_name": "100354449_19-06-2026.pdf",
      "tipo": "GRAND_CHEF",
      "zona": "GC_uOHxJZtf11XNKRCRQbSs",
      "gc_colli": "",
      "gc_peso_kg": "26.3",
      "gc_num_cartone": "",
      "orario_min": "08:00",
      "orario_max": "12:00",
      "note": ""
    },
    {
      "codice_consegna": "100353327",
      "data": "19-06-2026",
      "num_ddt": "GC_100353327",
      "pdf_name": "100353327_19-06-2026.pdf",
      "tipo": "GRAND_CHEF",
      "zona": "GC_uOHxJZtf11XNKRCRQbSs",
      "gc_colli": "",
      "gc_peso_kg": "29.75",
      "gc_num_cartone": "",
      "orario_min": "09:30",
      "orario_max": "11:00",
      "note": "tel. 3200222213"
    },
    {
      "codice_consegna": "100354203",
      "data": "19-06-2026",
      "num_ddt": "GC_100354203",
      "pdf_name": "100354203_19-06-2026.pdf",
      "tipo": "GRAND_CHEF",
      "zona": "GC_uOHxJZtf11XNKRCRQbSs",
      "gc_colli": "",
      "gc_peso_kg": "38",
      "gc_num_cartone": "",
      "orario_min": "09:00",
      "orario_max": "12:00",
      "note": ""
    },
    {
      "codice_consegna": "100350486",
      "data": "19-06-2026",
      "num_ddt": "GC_100350486",
      "pdf_name": "100350486_19-06-2026.pdf",
      "tipo": "GRAND_CHEF",
      "zona": "GC_uOHxJZtf11XNKRCRQbSs",
      "gc_colli": "",
      "gc_peso_kg": "94.22",
      "gc_num_cartone": "436",
      "orario_min": "07:10",
      "orario_max": "10:30",
      "note": ""
    },
    {
      "codice_consegna": "100351316",
      "data": "19-06-2026",
      "num_ddt": "GC_100351316",
      "pdf_name": "100351316_19-06-2026.pdf",
      "tipo": "GRAND_CHEF",
      "zona": "GC_uOHxJZtf11XNKRCRQbSs",
      "gc_colli": "1",
      "gc_peso_kg": "34.42",
      "gc_num_cartone": "",
      "orario_min": "07:30",
      "orario_max": "10:00",
      "note": "consegnare nei padiglioni uffici"
    },
    {
      "codice_consegna": "100350880",
      "data": "19-06-2026",
      "num_ddt": "GC_100350880",
      "pdf_name": "100350880_19-06-2026.pdf",
      "tipo": "GRAND_CHEF",
      "zona": "GC_uOHxJZtf11XNKRCRQbSs",
      "gc_colli": "",
      "gc_peso_kg": "40.9",
      "gc_num_cartone": "",
      "orario_min": "06:30",
      "orario_max": "09:00",
      "note": "non dopo le 9 chiamare 3246846506"
    },
    {
      "codice_consegna": "100350964",
      "data": "19-06-2026",
      "num_ddt": "GC_100350964",
      "pdf_name": "100350964_19-06-2026.pdf",
      "tipo": "GRAND_CHEF",
      "zona": "GC_uOHxJZtf11XNKRCRQbSs",
      "gc_colli": "",
      "gc_peso_kg": "13.8",
      "gc_num_cartone": "",
      "orario_min": "09:00",
      "orario_max": "14:00",
      "note": ""
    },
    {
      "codice_consegna": "100341080",
      "data": "19-06-2026",
      "num_ddt": "GC_100341080",
      "pdf_name": "100341080_19-06-2026.pdf",
      "tipo": "GRAND_CHEF",
      "zona": "GC_uOHxJZtf11XNKRCRQbSs",
      "gc_colli": "",
      "gc_peso_kg": "13.42",
      "gc_num_cartone": "124",
      "orario_min": "08:30",
      "orario_max": "10:30",
      "note": ""
    },
    {
      "codice_consegna": "100351139",
      "data": "19-06-2026",
      "num_ddt": "GC_100351139",
      "pdf_name": "100351139_19-06-2026.pdf",
      "tipo": "GRAND_CHEF",
      "zona": "GC_uOHxJZtf11XNKRCRQbSs",
      "gc_colli": "",
      "gc_peso_kg": "18.778",
      "gc_num_cartone": "",
      "orario_min": "",
      "orario_max": "14:00",
      "note": ""
    },
    {
      "codice_consegna": "100351916",
      "data": "19-06-2026",
      "num_ddt": "GC_100351916",
      "pdf_name": "100351916_19-06-2026.pdf",
      "tipo": "GRAND_CHEF",
      "zona": "GC_uOHxJZtf11XNKRCRQbSs",
      "gc_colli": "1",
      "gc_peso_kg": "23.904",
      "gc_num_cartone": "",
      "orario_min": "10:00",
      "orario_max": "14:00",
      "note": ""
    },
    {
      "codice_consegna": "100348449",
      "data": "19-06-2026",
      "num_ddt": "GC_100348449",
      "pdf_name": "100348449_19-06-2026.pdf",
      "tipo": "GRAND_CHEF",
      "zona": "GC_uOHxJZtf11XNKRCRQbSs",
      "gc_colli": "1",
      "gc_peso_kg": "52.67",
      "gc_num_cartone": "120",
      "orario_min": "",
      "orario_max": "14:00",
      "note": "tel. 3495589014 chiamare15min prima"
    },
    {
      "codice_consegna": "100348794",
      "data": "19-06-2026",
      "num_ddt": "GC_100348794",
      "pdf_name": "100348794_19-06-2026.pdf",
      "tipo": "GRAND_CHEF",
      "zona": "GC_uOHxJZtf11XNKRCRQbSs",
      "gc_colli": "",
      "gc_peso_kg": "34.7",
      "gc_num_cartone": "118",
      "orario_min": "",
      "orario_max": "14:00",
      "note": "PREAVV. 15MIN PRIMA"
    },
    {
      "codice_consegna": "100348795",
      "data": "19-06-2026",
      "num_ddt": "GC_100348795",
      "pdf_name": "100348795_19-06-2026.pdf",
      "tipo": "GRAND_CHEF",
      "zona": "GC_uOHxJZtf11XNKRCRQbSs",
      "gc_colli": "",
      "gc_peso_kg": "148.235",
      "gc_num_cartone": "119",
      "orario_min": "",
      "orario_max": "14:00",
      "note": "PREAVV. 15MIN PRIMA"
    },
    {
      "codice_consegna": "100354108",
      "data": "19-06-2026",
      "num_ddt": "GC_100354108",
      "pdf_name": "100354108_19-06-2026.pdf",
      "tipo": "GRAND_CHEF",
      "zona": "GC_uOHxJZtf11XNKRCRQbSs",
      "gc_colli": "",
      "gc_peso_kg": "59.204",
      "gc_num_cartone": "",
      "orario_min": "08:30",
      "orario_max": "11:30",
      "note": "o dopo le 14:30 tel prima3428417505"
    },
    {
      "codice_consegna": "100354355",
      "data": "19-06-2026",
      "num_ddt": "GC_100354355",
      "pdf_name": "100354355_19-06-2026.pdf",
      "tipo": "GRAND_CHEF",
      "zona": "GC_uOHxJZtf11XNKRCRQbSs",
      "gc_colli": "",
      "gc_peso_kg": "26.432",
      "gc_num_cartone": "",
      "orario_min": "07:00",
      "orario_max": "09:00",
      "note": "oppure dopo le 11"
    },
    {
      "codice_consegna": "100355338",
      "data": "19-06-2026",
      "num_ddt": "GC_100355338",
      "pdf_name": "100355338_19-06-2026.pdf",
      "tipo": "GRAND_CHEF",
      "zona": "GC_uOHxJZtf11XNKRCRQbSs",
      "gc_colli": "1",
      "gc_peso_kg": "12.1",
      "gc_num_cartone": "",
      "orario_min": "10:00",
      "orario_max": "14:00",
      "note": ""
    }
  ]
}